jumonc_llview/jumonc_llview_plugin.py
jumonc_llview/verifyLLView.py
jumonc_llview-0.3.1rc1.dist-info/LICENSE
jumonc_llview-0.3.1rc1.dist-info/METADATA
jumonc_llview-0.3.1rc1.dist-info/WHEEL
jumonc_llview-0.3.1rc1.dist-info/entry_points.txt
jumonc_llview-0.3.1rc1.dist-info/top_level.txt
jumonc_llview-0.3.1rc1.dist-info/RECORD
