Metadata-Version: 2.1
Name: jumonc-llview
Version: 0.3.1rc1
Summary: Allow LLVIEW to querry API-paths to be used for the job reporting
Home-page: https://gitlab.jsc.fz-juelich.de/coec/jumonc_llview
Author: Christian Witzler
Author-email: c.witzler@fz-juelich.de
License: BSD 3-Clause License
Platform: UNKNOWN
Classifier: License :: OSI Approved :: BSD License
Classifier: Programming Language :: Python :: 3
Classifier: Programming Language :: Python :: 3.9
Requires-Dist: JuMonC (>=0.10.0rc5)
Requires-Dist: pluggy
Requires-Dist: pycryptodome
